campfire/__init__.py
campfire/config.json
campfire/components/__init__.py
campfire/components/cert.pem
campfire/components/config.py
campfire/components/exceptions.py
campfire/components/main.py
campfire/components/request.py
campfire/components/firebase/__init__.py
campfire/components/firebase/firebase.py
campfire/components/firebase/notifications.py
campfire/components/firebase/proto/__init__.py
campfire/components/firebase/proto/android_checkin.proto
campfire/components/firebase/proto/android_checkin_pb2.py
campfire/components/firebase/proto/checkin.proto
campfire/components/firebase/proto/checkin_pb2.py
campfire/components/firebase/proto/mcs.proto
campfire/components/firebase/proto/mcs_pb2.py
campfire/components/tools/__init__.py
campfire/components/tools/file.py
campfire_basic-1.1.2.dist-info/LICENSE
campfire_basic-1.1.2.dist-info/METADATA
campfire_basic-1.1.2.dist-info/WHEEL
campfire_basic-1.1.2.dist-info/top_level.txt
campfire_basic-1.1.2.dist-info/RECORD
