Metadata-Version: 2.1
Name: campfire-basic
Version: 1.1.2
Summary: Campfire API basic functions
Author-email: Camper-CoolDie <campercooldie@gmail.com>
License: MIT License
Project-URL: Homepage, https://github.com/Camper-CoolDie/campfire-basic
Classifier: Programming Language :: Python :: 3
Classifier: Programming Language :: Python :: 3.7
Classifier: Programming Language :: Python :: 3.8
Classifier: Programming Language :: Python :: 3.9
Classifier: License :: OSI Approved :: MIT License
Classifier: Operating System :: OS Independent
Classifier: Typing :: Typed
Requires-Python: >=3.7
License-File: LICENSE
Provides-Extra: notifications
Requires-Dist: cryptography (>=3.1) ; extra == 'notifications'
Requires-Dist: oscrypto ; extra == 'notifications'
Requires-Dist: http-ece ; extra == 'notifications'
Requires-Dist: protobuf (<=3.20) ; extra == 'notifications'
